README.md
birdyaml.py
setup.cfg
setup.py
birdyaml.egg-info/PKG-INFO
birdyaml.egg-info/SOURCES.txt
birdyaml.egg-info/dependency_links.txt
birdyaml.egg-info/requires.txt
birdyaml.egg-info/top_level.txt